Workbook
Name CompsInput: Dashboard!$C$4
Name CompsNumPeers: Dashboard!$C$5
Name CompsCustomPeers: Dashboard!$C$6
Name CompsStatus: Dashboard!$B$9
Name CompsSubtitle: Dashboard!$B$12
Name CompsProfile: Dashboard!$C$17
Name CompsProfileWhy: Dashboard!$B$18
Name CompsMultiples: Dashboard!$B$21:$C$26
Name CompsNotes: Dashboard!$B$33
Name CompsPeerTable: Dashboard!$B$38:$G$45
Name CompsData: Comps!$A$6:$T$14
Name CompsScreen: 'Peer Screen'!$A$5:$N$29

Sheet Dashboard
B2: SMIF Comps Analyzer
B4: Company name or ticker | C4: AMZN | E4: ① Type a company or ticker in the yellow cell
B5: Number of peers (3–8) | C5: 5 | E5: ② Click the xlwings tab → Run main (or your Refresh button)
B6: Custom peers (optional) | E6: ③ Leave custom peers blank to auto-pick, or list tickers: MSFT, GOOGL
B9: SAMPLE DATA (illustrative, not live) – type a company in the yellow cell, then click xlwings ▸ Run main to load live Yahoo Finance data.
B11: =IF(Comps!$A$6="","",Comps!$B$6&" ("&Comps!$A$6&")")
B12: Consumer Cyclical · Internet Retail · USD
B14: Share price | C14: Market cap ($mm) | D14: Enterprise value ($mm) | E14: Revenue growth | F14: EBITDA margin | G14: Net margin
B15: =Comps!C6 | C15: =Comps!D6 | D15: =Comps!V6 | E15: =Comps!Q6 | F15: =Comps!S6 | G15: =Comps!T6
B17: Valuation profile | C17: Mature
B18: Profitable, established business: standard enterprise and equity earnings multiples apply, with P/FCF as a cash sanity check.
B20: Multiple (pick from list) | C20: Use in blend | D20: Target | E20: Peer median | F20: Premium / (discount) | G20: Implied price @ median | H20: Upside | I20: Why this multiple
B21: EV / EBITDA | C21: Y | D21: =IF($B21="","",Valuation!E9) | E21: =IF($B21="","",Valuation!G9) | F21: =IF($B21="","",IF(AND(ISNUMBER(D21),ISNUMBER(E21)),D21/E21-1,"NM")) | G21: =IF($B21="","",Valuation!J9) | H21: =IF($B21="","",Valuation!L9) | I21: =IF($B21="","",IFERROR(INDEX(Lists!$D$2:$D$11,MATCH($B21,Lists!$A$2:$A$11,0)),""))
B22: P / E (Forward) | C22: Y | D22: =IF($B22="","",Valuation!E10) | E22: =IF($B22="","",Valuation!G10) | F22: =IF($B22="","",IF(AND(ISNUMBER(D22),ISNUMBER(E22)),D22/E22-1,"NM")) | G22: =IF($B22="","",Valuation!J10) | H22: =IF($B22="","",Valuation!L10) | I22: =IF($B22="","",IFERROR(INDEX(Lists!$D$2:$D$11,MATCH($B22,Lists!$A$2:$A$11,0)),""))
B23: EV / EBIT | C23: Y | D23: =IF($B23="","",Valuation!E11) | E23: =IF($B23="","",Valuation!G11) | F23: =IF($B23="","",IF(AND(ISNUMBER(D23),ISNUMBER(E23)),D23/E23-1,"NM")) | G23: =IF($B23="","",Valuation!J11) | H23: =IF($B23="","",Valuation!L11) | I23: =IF($B23="","",IFERROR(INDEX(Lists!$D$2:$D$11,MATCH($B23,Lists!$A$2:$A$11,0)),""))
B24: P / E (LTM) | C24: N | D24: =IF($B24="","",Valuation!E12) | E24: =IF($B24="","",Valuation!G12) | F24: =IF($B24="","",IF(AND(ISNUMBER(D24),ISNUMBER(E24)),D24/E24-1,"NM")) | G24: =IF($B24="","",Valuation!J12) | H24: =IF($B24="","",Valuation!L12) | I24: =IF($B24="","",IFERROR(INDEX(Lists!$D$2:$D$11,MATCH($B24,Lists!$A$2:$A$11,0)),""))
B25: P / FCF | C25: N | D25: =IF($B25="","",Valuation!E13) | E25: =IF($B25="","",Valuation!G13) | F25: =IF($B25="","",IF(AND(ISNUMBER(D25),ISNUMBER(E25)),D25/E25-1,"NM")) | G25: =IF($B25="","",Valuation!J13) | H25: =IF($B25="","",Valuation!L13) | I25: =IF($B25="","",IFERROR(INDEX(Lists!$D$2:$D$11,MATCH($B25,Lists!$A$2:$A$11,0)),""))
D26: =IF($B26="","",Valuation!E14) | E26: =IF($B26="","",Valuation!G14) | F26: =IF($B26="","",IF(AND(ISNUMBER(D26),ISNUMBER(E26)),D26/E26-1,"NM")) | G26: =IF($B26="","",Valuation!J14) | H26: =IF($B26="","",Valuation!L14) | I26: =IF($B26="","",IFERROR(INDEX(Lists!$D$2:$D$11,MATCH($B26,Lists!$A$2:$A$11,0)),""))
B28: Blended implied price ('Y' multiples, peer median) | G28: =Valuation!J16 | H28: =Valuation!L16
B30: =IF(OR(Comps!$A$6="",NOT(ISNUMBER(G28))),"Refresh to see the summary.",Comps!$A$6&" trades at "&TEXT(Comps!$C$6,"#,##0.00")&" vs. "&TEXT(G28,"#,##0.00")&" implied by peer-median multiples: a "&TEXT(ABS(Comps!$C$6/G28-1),"0%")&IF(Comps!$C$6>=G28," premium"," discount")&" to the blended peer-implied value.")
B32: Analyst notes (written at refresh)
B33: On its key multiples, AMZN trades at a 97% premium to the peer median (median across those multiples; peers: BABA, PDD, MELI, EBAY, CPNG). That premium is consistent with its higher EBITDA margins (22% vs 18%). Applying peer-median multiples implies ~USD 130.46/share vs. 225.00 today (-42%).
B37: Peer company | C37: Ticker | D37: Industry | E37: Market cap ($mm) | F37: Similarity (0–100) | G37: Why it's a comp
B38: Alibaba Group Holding Limited | C38: BABA | D38: Internet Retail | E38: 320000 | F38: 75.2 | G38: Same industry (Internet Retail); Similar revenue growth (6% vs 11%); Similar EBITDA margin (18% vs 22%)
B39: PDD Holdings Inc. | C39: PDD | D39: Internet Retail | E39: 170000 | F39: 73.3 | G39: Same industry (Internet Retail); Similar revenue growth (10% vs 11%)
B40: MercadoLibre, Inc. | C40: MELI | D40: Internet Retail | E40: 120000 | F40: 60.9 | G40: Same industry (Internet Retail); Similar gross margin (46% vs 49%)
B41: eBay Inc. | C41: EBAY | D41: Internet Retail | E41: 41000 | F41: 60.3 | G41: Same industry (Internet Retail)
B42: Coupang, Inc. | C42: CPNG | D42: Internet Retail | E42: 54000 | F42: 59.7 | G42: Same industry (Internet Retail)
B47: Blue = written by Refresh · Yellow = your inputs · Green = links · Black = formulas. Data: Yahoo Finance – verify key figures against filings before presenting.

Sheet Comps
A1: Comparable Companies Analysis
A2: $ in millions except per share (reporting currency converted to trading currency). Blue = input written by Refresh (safe to overwrite), black = formula. Highlighted headers = multiples picked on the Dashboard.
V4: NM if above → | W4: 60 | X4: 60 | Y4: 80 | Z4: 100 | AA4: 150 | AB4: 150 | AC4: 150 | AD4: 150 | AE4: 100 | AF4: 50
A5: Ticker | B5: Company | C5: Share Price | D5: Market Cap ($mm) | E5: Total Debt ($mm) | F5: Cash ($mm) | G5: LTM Revenue ($mm) | H5: NTM Revenue ($mm) | I5: LTM Gross Profit ($mm) | J5: LTM EBITDA ($mm) | K5: LTM EBIT ($mm) | L5: LTM Net Income ($mm) | M5: Forward Earnings ($mm) | N5: LTM Op. Cash Flow ($mm) | O5: LTM FCF ($mm) | P5: Book Value ($mm) | Q5: Revenue Growth | R5: Gross Margin | S5: EBITDA Margin | T5: Net Margin | V5: Enterprise Value ($mm) | W5: EV / LTM Revenue | X5: EV / NTM Revenue | Y5: EV / Gross Profit | Z5: EV / EBITDA | AA5: EV / EBIT | AB5: P / E (LTM) | AC5: P / E (Forward) | AD5: P / FCF | AE5: P / Operating Cash Flow | AF5: P / Book
A6: AMZN | B6: Amazon.com, Inc. | C6: 225 | D6: 2400000 | E6: 160000 | F6: 95000 | G6: 670000 | H6: 735000 | I6: 330000 | J6: 145000 | K6: 76000 | L6: 70000 | M6: 72727.273 | N6: 125000 | O6: 25000 | P6: 330000 | Q6: 0.11 | R6: 0.49253731 | S6: 0.21641791 | T6: 0.10447761 | V6: =IF($A6="","",IF(ISNUMBER(D6),D6+N(E6)-N(F6),"NM")) | W6: =IF($A6="","",IF(AND(ISNUMBER(G6),ISNUMBER(V6)),IF(AND(G6>0,V6>0),IF(V6/G6<=W$4,V6/G6,"NM"),"NM"),"NM")) | X6: =IF($A6="","",IF(AND(ISNUMBER(H6),ISNUMBER(V6)),IF(AND(H6>0,V6>0),IF(V6/H6<=X$4,V6/H6,"NM"),"NM"),"NM")) | Y6: =IF($A6="","",IF(AND(ISNUMBER(I6),ISNUMBER(V6)),IF(AND(I6>0,V6>0),IF(V6/I6<=Y$4,V6/I6,"NM"),"NM"),"NM")) | Z6: =IF($A6="","",IF(AND(ISNUMBER(J6),ISNUMBER(V6)),IF(AND(J6>0,V6>0),IF(V6/J6<=Z$4,V6/J6,"NM"),"NM"),"NM")) | AA6: =IF($A6="","",IF(AND(ISNUMBER(K6),ISNUMBER(V6)),IF(AND(K6>0,V6>0),IF(V6/K6<=AA$4,V6/K6,"NM"),"NM"),"NM")) | AB6: =IF($A6="","",IF(AND(ISNUMBER(L6),ISNUMBER(D6)),IF(AND(L6>0,D6>0),IF(D6/L6<=AB$4,D6/L6,"NM"),"NM"),"NM")) | AC6: =IF($A6="","",IF(AND(ISNUMBER(M6),ISNUMBER(D6)),IF(AND(M6>0,D6>0),IF(D6/M6<=AC$4,D6/M6,"NM"),"NM"),"NM")) | AD6: =IF($A6="","",IF(AND(ISNUMBER(O6),ISNUMBER(D6)),IF(AND(O6>0,D6>0),IF(D6/O6<=AD$4,D6/O6,"NM"),"NM"),"NM")) | AE6: =IF($A6="","",IF(AND(ISNUMBER(N6),ISNUMBER(D6)),IF(AND(N6>0,D6>0),IF(D6/N6<=AE$4,D6/N6,"NM"),"NM"),"NM")) | AF6: =IF($A6="","",IF(AND(ISNUMBER(P6),ISNUMBER(D6)),IF(AND(P6>0,D6>0),IF(D6/P6<=AF$4,D6/P6,"NM"),"NM"),"NM"))
A7: BABA | B7: Alibaba Group Holding Limited | C7: 135 | D7: 320000 | E7: 35000 | F7: 75000 | G7: 138000 | H7: 150000 | I7: 55000 | J7: 25000 | K7: 17000 | L7: 17000 | M7: 22857.143 | N7: 22000 | O7: 8000 | P7: 135000 | Q7: 0.06 | R7: 0.39855072 | S7: 0.18115942 | T7: 0.12318841 | V7: =IF($A7="","",IF(ISNUMBER(D7),D7+N(E7)-N(F7),"NM")) | W7: =IF($A7="","",IF(AND(ISNUMBER(G7),ISNUMBER(V7)),IF(AND(G7>0,V7>0),IF(V7/G7<=W$4,V7/G7,"NM"),"NM"),"NM")) | X7: =IF($A7="","",IF(AND(ISNUMBER(H7),ISNUMBER(V7)),IF(AND(H7>0,V7>0),IF(V7/H7<=X$4,V7/H7,"NM"),"NM"),"NM")) | Y7: =IF($A7="","",IF(AND(ISNUMBER(I7),ISNUMBER(V7)),IF(AND(I7>0,V7>0),IF(V7/I7<=Y$4,V7/I7,"NM"),"NM"),"NM")) | Z7: =IF($A7="","",IF(AND(ISNUMBER(J7),ISNUMBER(V7)),IF(AND(J7>0,V7>0),IF(V7/J7<=Z$4,V7/J7,"NM"),"NM"),"NM")) | AA7: =IF($A7="","",IF(AND(ISNUMBER(K7),ISNUMBER(V7)),IF(AND(K7>0,V7>0),IF(V7/K7<=AA$4,V7/K7,"NM"),"NM"),"NM")) | AB7: =IF($A7="","",IF(AND(ISNUMBER(L7),ISNUMBER(D7)),IF(AND(L7>0,D7>0),IF(D7/L7<=AB$4,D7/L7,"NM"),"NM"),"NM")) | AC7: =IF($A7="","",IF(AND(ISNUMBER(M7),ISNUMBER(D7)),IF(AND(M7>0,D7>0),IF(D7/M7<=AC$4,D7/M7,"NM"),"NM"),"NM")) | AD7: =IF($A7="","",IF(AND(ISNUMBER(O7),ISNUMBER(D7)),IF(AND(O7>0,D7>0),IF(D7/O7<=AD$4,D7/O7,"NM"),"NM"),"NM")) | AE7: =IF($A7="","",IF(AND(ISNUMBER(N7),ISNUMBER(D7)),IF(AND(N7>0,D7>0),IF(D7/N7<=AE$4,D7/N7,"NM"),"NM"),"NM")) | AF7: =IF($A7="","",IF(AND(ISNUMBER(P7),ISNUMBER(D7)),IF(AND(P7>0,D7>0),IF(D7/P7<=AF$4,D7/P7,"NM"),"NM"),"NM"))
A8: PDD | B8: PDD Holdings Inc. | C8: 120 | D8: 170000 | E8: 2000 | F8: 50000 | G8: 56000 | H8: 63000 | I8: 33000 | J8: 16000 | K8: 15000 | L8: 15000 | M8: 17000 | N8: 16000 | O8: 15000 | P8: 45000 | Q8: 0.1 | R8: 0.58928571 | S8: 0.28571429 | T8: 0.26785714 | V8: =IF($A8="","",IF(ISNUMBER(D8),D8+N(E8)-N(F8),"NM")) | W8: =IF($A8="","",IF(AND(ISNUMBER(G8),ISNUMBER(V8)),IF(AND(G8>0,V8>0),IF(V8/G8<=W$4,V8/G8,"NM"),"NM"),"NM")) | X8: =IF($A8="","",IF(AND(ISNUMBER(H8),ISNUMBER(V8)),IF(AND(H8>0,V8>0),IF(V8/H8<=X$4,V8/H8,"NM"),"NM"),"NM")) | Y8: =IF($A8="","",IF(AND(ISNUMBER(I8),ISNUMBER(V8)),IF(AND(I8>0,V8>0),IF(V8/I8<=Y$4,V8/I8,"NM"),"NM"),"NM")) | Z8: =IF($A8="","",IF(AND(ISNUMBER(J8),ISNUMBER(V8)),IF(AND(J8>0,V8>0),IF(V8/J8<=Z$4,V8/J8,"NM"),"NM"),"NM")) | AA8: =IF($A8="","",IF(AND(ISNUMBER(K8),ISNUMBER(V8)),IF(AND(K8>0,V8>0),IF(V8/K8<=AA$4,V8/K8,"NM"),"NM"),"NM")) | AB8: =IF($A8="","",IF(AND(ISNUMBER(L8),ISNUMBER(D8)),IF(AND(L8>0,D8>0),IF(D8/L8<=AB$4,D8/L8,"NM"),"NM"),"NM")) | AC8: =IF($A8="","",IF(AND(ISNUMBER(M8),ISNUMBER(D8)),IF(AND(M8>0,D8>0),IF(D8/M8<=AC$4,D8/M8,"NM"),"NM"),"NM")) | AD8: =IF($A8="","",IF(AND(ISNUMBER(O8),ISNUMBER(D8)),IF(AND(O8>0,D8>0),IF(D8/O8<=AD$4,D8/O8,"NM"),"NM"),"NM")) | AE8: =IF($A8="","",IF(AND(ISNUMBER(N8),ISNUMBER(D8)),IF(AND(N8>0,D8>0),IF(D8/N8<=AE$4,D8/N8,"NM"),"NM"),"NM")) | AF8: =IF($A8="","",IF(AND(ISNUMBER(P8),ISNUMBER(D8)),IF(AND(P8>0,D8>0),IF(D8/P8<=AF$4,D8/P8,"NM"),"NM"),"NM"))
A9: MELI | B9: MercadoLibre, Inc. | C9: 2400 | D9: 120000 | E9: 8000 | F9: 9000 | G9: 24000 | H9: 30000 | I9: 11000 | J9: 3600 | K9: 3000 | L9: 2000 | M9: 2666.6667 | N9: 7000 | O9: 6000 | P9: 5000 | Q9: 0.37 | R9: 0.45833333 | S9: 0.15 | T9: 0.083333333 | V9: =IF($A9="","",IF(ISNUMBER(D9),D9+N(E9)-N(F9),"NM")) | W9: =IF($A9="","",IF(AND(ISNUMBER(G9),ISNUMBER(V9)),IF(AND(G9>0,V9>0),IF(V9/G9<=W$4,V9/G9,"NM"),"NM"),"NM")) | X9: =IF($A9="","",IF(AND(ISNUMBER(H9),ISNUMBER(V9)),IF(AND(H9>0,V9>0),IF(V9/H9<=X$4,V9/H9,"NM"),"NM"),"NM")) | Y9: =IF($A9="","",IF(AND(ISNUMBER(I9),ISNUMBER(V9)),IF(AND(I9>0,V9>0),IF(V9/I9<=Y$4,V9/I9,"NM"),"NM"),"NM")) | Z9: =IF($A9="","",IF(AND(ISNUMBER(J9),ISNUMBER(V9)),IF(AND(J9>0,V9>0),IF(V9/J9<=Z$4,V9/J9,"NM"),"NM"),"NM")) | AA9: =IF($A9="","",IF(AND(ISNUMBER(K9),ISNUMBER(V9)),IF(AND(K9>0,V9>0),IF(V9/K9<=AA$4,V9/K9,"NM"),"NM"),"NM")) | AB9: =IF($A9="","",IF(AND(ISNUMBER(L9),ISNUMBER(D9)),IF(AND(L9>0,D9>0),IF(D9/L9<=AB$4,D9/L9,"NM"),"NM"),"NM")) | AC9: =IF($A9="","",IF(AND(ISNUMBER(M9),ISNUMBER(D9)),IF(AND(M9>0,D9>0),IF(D9/M9<=AC$4,D9/M9,"NM"),"NM"),"NM")) | AD9: =IF($A9="","",IF(AND(ISNUMBER(O9),ISNUMBER(D9)),IF(AND(O9>0,D9>0),IF(D9/O9<=AD$4,D9/O9,"NM"),"NM"),"NM")) | AE9: =IF($A9="","",IF(AND(ISNUMBER(N9),ISNUMBER(D9)),IF(AND(N9>0,D9>0),IF(D9/N9<=AE$4,D9/N9,"NM"),"NM"),"NM")) | AF9: =IF($A9="","",IF(AND(ISNUMBER(P9),ISNUMBER(D9)),IF(AND(P9>0,D9>0),IF(D9/P9<=AF$4,D9/P9,"NM"),"NM"),"NM"))
A10: EBAY | B10: eBay Inc. | C10: 90 | D10: 41000 | E10: 8000 | F10: 6000 | G10: 10500 | H10: 11000 | I10: 7400 | J10: 3300 | K10: 2800 | L10: 2100 | M10: 2562.5 | N10: 2500 | O10: 2100 | P10: 5000 | Q10: 0.04 | R10: 0.7047619 | S10: 0.31428571 | T10: 0.2 | V10: =IF($A10="","",IF(ISNUMBER(D10),D10+N(E10)-N(F10),"NM")) | W10: =IF($A10="","",IF(AND(ISNUMBER(G10),ISNUMBER(V10)),IF(AND(G10>0,V10>0),IF(V10/G10<=W$4,V10/G10,"NM"),"NM"),"NM")) | X10: =IF($A10="","",IF(AND(ISNUMBER(H10),ISNUMBER(V10)),IF(AND(H10>0,V10>0),IF(V10/H10<=X$4,V10/H10,"NM"),"NM"),"NM")) | Y10: =IF($A10="","",IF(AND(ISNUMBER(I10),ISNUMBER(V10)),IF(AND(I10>0,V10>0),IF(V10/I10<=Y$4,V10/I10,"NM"),"NM"),"NM")) | Z10: =IF($A10="","",IF(AND(ISNUMBER(J10),ISNUMBER(V10)),IF(AND(J10>0,V10>0),IF(V10/J10<=Z$4,V10/J10,"NM"),"NM"),"NM")) | AA10: =IF($A10="","",IF(AND(ISNUMBER(K10),ISNUMBER(V10)),IF(AND(K10>0,V10>0),IF(V10/K10<=AA$4,V10/K10,"NM"),"NM"),"NM")) | AB10: =IF($A10="","",IF(AND(ISNUMBER(L10),ISNUMBER(D10)),IF(AND(L10>0,D10>0),IF(D10/L10<=AB$4,D10/L10,"NM"),"NM"),"NM")) | AC10: =IF($A10="","",IF(AND(ISNUMBER(M10),ISNUMBER(D10)),IF(AND(M10>0,D10>0),IF(D10/M10<=AC$4,D10/M10,"NM"),"NM"),"NM")) | AD10: =IF($A10="","",IF(AND(ISNUMBER(O10),ISNUMBER(D10)),IF(AND(O10>0,D10>0),IF(D10/O10<=AD$4,D10/O10,"NM"),"NM"),"NM")) | AE10: =IF($A10="","",IF(AND(ISNUMBER(N10),ISNUMBER(D10)),IF(AND(N10>0,D10>0),IF(D10/N10<=AE$4,D10/N10,"NM"),"NM"),"NM")) | AF10: =IF($A10="","",IF(AND(ISNUMBER(P10),ISNUMBER(D10)),IF(AND(P10>0,D10>0),IF(D10/P10<=AF$4,D10/P10,"NM"),"NM"),"NM"))
A11: CPNG | B11: Coupang, Inc. | C11: 30 | D11: 54000 | E11: 3000 | F11: 6000 | G11: 33000 | H11: 38000 | I11: 10000 | J11: 1600 | K11: 600 | L11: 200 | M11: 900 | N11: 2000 | O11: 900 | P11: 4000 | Q11: 0.18 | R11: 0.3030303 | S11: 0.048484848 | T11: 0.0060606061 | V11: =IF($A11="","",IF(ISNUMBER(D11),D11+N(E11)-N(F11),"NM")) | W11: =IF($A11="","",IF(AND(ISNUMBER(G11),ISNUMBER(V11)),IF(AND(G11>0,V11>0),IF(V11/G11<=W$4,V11/G11,"NM"),"NM"),"NM")) | X11: =IF($A11="","",IF(AND(ISNUMBER(H11),ISNUMBER(V11)),IF(AND(H11>0,V11>0),IF(V11/H11<=X$4,V11/H11,"NM"),"NM"),"NM")) | Y11: =IF($A11="","",IF(AND(ISNUMBER(I11),ISNUMBER(V11)),IF(AND(I11>0,V11>0),IF(V11/I11<=Y$4,V11/I11,"NM"),"NM"),"NM")) | Z11: =IF($A11="","",IF(AND(ISNUMBER(J11),ISNUMBER(V11)),IF(AND(J11>0,V11>0),IF(V11/J11<=Z$4,V11/J11,"NM"),"NM"),"NM")) | AA11: =IF($A11="","",IF(AND(ISNUMBER(K11),ISNUMBER(V11)),IF(AND(K11>0,V11>0),IF(V11/K11<=AA$4,V11/K11,"NM"),"NM"),"NM")) | AB11: =IF($A11="","",IF(AND(ISNUMBER(L11),ISNUMBER(D11)),IF(AND(L11>0,D11>0),IF(D11/L11<=AB$4,D11/L11,"NM"),"NM"),"NM")) | AC11: =IF($A11="","",IF(AND(ISNUMBER(M11),ISNUMBER(D11)),IF(AND(M11>0,D11>0),IF(D11/M11<=AC$4,D11/M11,"NM"),"NM"),"NM")) | AD11: =IF($A11="","",IF(AND(ISNUMBER(O11),ISNUMBER(D11)),IF(AND(O11>0,D11>0),IF(D11/O11<=AD$4,D11/O11,"NM"),"NM"),"NM")) | AE11: =IF($A11="","",IF(AND(ISNUMBER(N11),ISNUMBER(D11)),IF(AND(N11>0,D11>0),IF(D11/N11<=AE$4,D11/N11,"NM"),"NM"),"NM")) | AF11: =IF($A11="","",IF(AND(ISNUMBER(P11),ISNUMBER(D11)),IF(AND(P11>0,D11>0),IF(D11/P11<=AF$4,D11/P11,"NM"),"NM"),"NM"))
V12: =IF($A12="","",IF(ISNUMBER(D12),D12+N(E12)-N(F12),"NM")) | W12: =IF($A12="","",IF(AND(ISNUMBER(G12),ISNUMBER(V12)),IF(AND(G12>0,V12>0),IF(V12/G12<=W$4,V12/G12,"NM"),"NM"),"NM")) | X12: =IF($A12="","",IF(AND(ISNUMBER(H12),ISNUMBER(V12)),IF(AND(H12>0,V12>0),IF(V12/H12<=X$4,V12/H12,"NM"),"NM"),"NM")) | Y12: =IF($A12="","",IF(AND(ISNUMBER(I12),ISNUMBER(V12)),IF(AND(I12>0,V12>0),IF(V12/I12<=Y$4,V12/I12,"NM"),"NM"),"NM")) | Z12: =IF($A12="","",IF(AND(ISNUMBER(J12),ISNUMBER(V12)),IF(AND(J12>0,V12>0),IF(V12/J12<=Z$4,V12/J12,"NM"),"NM"),"NM")) | AA12: =IF($A12="","",IF(AND(ISNUMBER(K12),ISNUMBER(V12)),IF(AND(K12>0,V12>0),IF(V12/K12<=AA$4,V12/K12,"NM"),"NM"),"NM")) | AB12: =IF($A12="","",IF(AND(ISNUMBER(L12),ISNUMBER(D12)),IF(AND(L12>0,D12>0),IF(D12/L12<=AB$4,D12/L12,"NM"),"NM"),"NM")) | AC12: =IF($A12="","",IF(AND(ISNUMBER(M12),ISNUMBER(D12)),IF(AND(M12>0,D12>0),IF(D12/M12<=AC$4,D12/M12,"NM"),"NM"),"NM")) | AD12: =IF($A12="","",IF(AND(ISNUMBER(O12),ISNUMBER(D12)),IF(AND(O12>0,D12>0),IF(D12/O12<=AD$4,D12/O12,"NM"),"NM"),"NM")) | AE12: =IF($A12="","",IF(AND(ISNUMBER(N12),ISNUMBER(D12)),IF(AND(N12>0,D12>0),IF(D12/N12<=AE$4,D12/N12,"NM"),"NM"),"NM")) | AF12: =IF($A12="","",IF(AND(ISNUMBER(P12),ISNUMBER(D12)),IF(AND(P12>0,D12>0),IF(D12/P12<=AF$4,D12/P12,"NM"),"NM"),"NM"))
V13: =IF($A13="","",IF(ISNUMBER(D13),D13+N(E13)-N(F13),"NM")) | W13: =IF($A13="","",IF(AND(ISNUMBER(G13),ISNUMBER(V13)),IF(AND(G13>0,V13>0),IF(V13/G13<=W$4,V13/G13,"NM"),"NM"),"NM")) | X13: =IF($A13="","",IF(AND(ISNUMBER(H13),ISNUMBER(V13)),IF(AND(H13>0,V13>0),IF(V13/H13<=X$4,V13/H13,"NM"),"NM"),"NM")) | Y13: =IF($A13="","",IF(AND(ISNUMBER(I13),ISNUMBER(V13)),IF(AND(I13>0,V13>0),IF(V13/I13<=Y$4,V13/I13,"NM"),"NM"),"NM")) | Z13: =IF($A13="","",IF(AND(ISNUMBER(J13),ISNUMBER(V13)),IF(AND(J13>0,V13>0),IF(V13/J13<=Z$4,V13/J13,"NM"),"NM"),"NM")) | AA13: =IF($A13="","",IF(AND(ISNUMBER(K13),ISNUMBER(V13)),IF(AND(K13>0,V13>0),IF(V13/K13<=AA$4,V13/K13,"NM"),"NM"),"NM")) | AB13: =IF($A13="","",IF(AND(ISNUMBER(L13),ISNUMBER(D13)),IF(AND(L13>0,D13>0),IF(D13/L13<=AB$4,D13/L13,"NM"),"NM"),"NM")) | AC13: =IF($A13="","",IF(AND(ISNUMBER(M13),ISNUMBER(D13)),IF(AND(M13>0,D13>0),IF(D13/M13<=AC$4,D13/M13,"NM"),"NM"),"NM")) | AD13: =IF($A13="","",IF(AND(ISNUMBER(O13),ISNUMBER(D13)),IF(AND(O13>0,D13>0),IF(D13/O13<=AD$4,D13/O13,"NM"),"NM"),"NM")) | AE13: =IF($A13="","",IF(AND(ISNUMBER(N13),ISNUMBER(D13)),IF(AND(N13>0,D13>0),IF(D13/N13<=AE$4,D13/N13,"NM"),"NM"),"NM")) | AF13: =IF($A13="","",IF(AND(ISNUMBER(P13),ISNUMBER(D13)),IF(AND(P13>0,D13>0),IF(D13/P13<=AF$4,D13/P13,"NM"),"NM"),"NM"))
V14: =IF($A14="","",IF(ISNUMBER(D14),D14+N(E14)-N(F14),"NM")) | W14: =IF($A14="","",IF(AND(ISNUMBER(G14),ISNUMBER(V14)),IF(AND(G14>0,V14>0),IF(V14/G14<=W$4,V14/G14,"NM"),"NM"),"NM")) | X14: =IF($A14="","",IF(AND(ISNUMBER(H14),ISNUMBER(V14)),IF(AND(H14>0,V14>0),IF(V14/H14<=X$4,V14/H14,"NM"),"NM"),"NM")) | Y14: =IF($A14="","",IF(AND(ISNUMBER(I14),ISNUMBER(V14)),IF(AND(I14>0,V14>0),IF(V14/I14<=Y$4,V14/I14,"NM"),"NM"),"NM")) | Z14: =IF($A14="","",IF(AND(ISNUMBER(J14),ISNUMBER(V14)),IF(AND(J14>0,V14>0),IF(V14/J14<=Z$4,V14/J14,"NM"),"NM"),"NM")) | AA14: =IF($A14="","",IF(AND(ISNUMBER(K14),ISNUMBER(V14)),IF(AND(K14>0,V14>0),IF(V14/K14<=AA$4,V14/K14,"NM"),"NM"),"NM")) | AB14: =IF($A14="","",IF(AND(ISNUMBER(L14),ISNUMBER(D14)),IF(AND(L14>0,D14>0),IF(D14/L14<=AB$4,D14/L14,"NM"),"NM"),"NM")) | AC14: =IF($A14="","",IF(AND(ISNUMBER(M14),ISNUMBER(D14)),IF(AND(M14>0,D14>0),IF(D14/M14<=AC$4,D14/M14,"NM"),"NM"),"NM")) | AD14: =IF($A14="","",IF(AND(ISNUMBER(O14),ISNUMBER(D14)),IF(AND(O14>0,D14>0),IF(D14/O14<=AD$4,D14/O14,"NM"),"NM"),"NM")) | AE14: =IF($A14="","",IF(AND(ISNUMBER(N14),ISNUMBER(D14)),IF(AND(N14>0,D14>0),IF(D14/N14<=AE$4,D14/N14,"NM"),"NM"),"NM")) | AF14: =IF($A14="","",IF(AND(ISNUMBER(P14),ISNUMBER(D14)),IF(AND(P14>0,D14>0),IF(D14/P14<=AF$4,D14/P14,"NM"),"NM"),"NM"))
B15: Peer statistics (excluding target)
B16: Maximum | Q16: =IF(COUNT(Q7:Q14)=0,"NM",MAX(Q7:Q14)) | R16: =IF(COUNT(R7:R14)=0,"NM",MAX(R7:R14)) | S16: =IF(COUNT(S7:S14)=0,"NM",MAX(S7:S14)) | T16: =IF(COUNT(T7:T14)=0,"NM",MAX(T7:T14)) | W16: =IF(COUNT(W7:W14)=0,"NM",MAX(W7:W14)) | X16: =IF(COUNT(X7:X14)=0,"NM",MAX(X7:X14)) | Y16: =IF(COUNT(Y7:Y14)=0,"NM",MAX(Y7:Y14)) | Z16: =IF(COUNT(Z7:Z14)=0,"NM",MAX(Z7:Z14)) | AA16: =IF(COUNT(AA7:AA14)=0,"NM",MAX(AA7:AA14)) | AB16: =IF(COUNT(AB7:AB14)=0,"NM",MAX(AB7:AB14)) | AC16: =IF(COUNT(AC7:AC14)=0,"NM",MAX(AC7:AC14)) | AD16: =IF(COUNT(AD7:AD14)=0,"NM",MAX(AD7:AD14)) | ... AF16: =IF(COUNT(AF7:AF14)=0,"NM",MAX(AF7:AF14))
B17: 75th Percentile | Q17: =IF(COUNT(Q7:Q14)=0,"NM",PERCENTILE(Q7:Q14,0.75)) | R17: =IF(COUNT(R7:R14)=0,"NM",PERCENTILE(R7:R14,0.75)) | S17: =IF(COUNT(S7:S14)=0,"NM",PERCENTILE(S7:S14,0.75)) | T17: =IF(COUNT(T7:T14)=0,"NM",PERCENTILE(T7:T14,0.75)) | W17: =IF(COUNT(W7:W14)=0,"NM",PERCENTILE(W7:W14,0.75)) | X17: =IF(COUNT(X7:X14)=0,"NM",PERCENTILE(X7:X14,0.75)) | Y17: =IF(COUNT(Y7:Y14)=0,"NM",PERCENTILE(Y7:Y14,0.75)) | Z17: =IF(COUNT(Z7:Z14)=0,"NM",PERCENTILE(Z7:Z14,0.75)) | AA17: =IF(COUNT(AA7:AA14)=0,"NM",PERCENTILE(AA7:AA14,0.75)) | AB17: =IF(COUNT(AB7:AB14)=0,"NM",PERCENTILE(AB7:AB14,0.75)) | AC17: =IF(COUNT(AC7:AC14)=0,"NM",PERCENTILE(AC7:AC14,0.75)) | AD17: =IF(COUNT(AD7:AD14)=0,"NM",PERCENTILE(AD7:AD14,0.75)) | ... AF17: =IF(COUNT(AF7:AF14)=0,"NM",PERCENTILE(AF7:AF14,0.75))
B18: Mean | Q18: =IF(COUNT(Q7:Q14)=0,"NM",AVERAGE(Q7:Q14)) | R18: =IF(COUNT(R7:R14)=0,"NM",AVERAGE(R7:R14)) | S18: =IF(COUNT(S7:S14)=0,"NM",AVERAGE(S7:S14)) | T18: =IF(COUNT(T7:T14)=0,"NM",AVERAGE(T7:T14)) | W18: =IF(COUNT(W7:W14)=0,"NM",AVERAGE(W7:W14)) | X18: =IF(COUNT(X7:X14)=0,"NM",AVERAGE(X7:X14)) | Y18: =IF(COUNT(Y7:Y14)=0,"NM",AVERAGE(Y7:Y14)) | Z18: =IF(COUNT(Z7:Z14)=0,"NM",AVERAGE(Z7:Z14)) | AA18: =IF(COUNT(AA7:AA14)=0,"NM",AVERAGE(AA7:AA14)) | AB18: =IF(COUNT(AB7:AB14)=0,"NM",AVERAGE(AB7:AB14)) | AC18: =IF(COUNT(AC7:AC14)=0,"NM",AVERAGE(AC7:AC14)) | AD18: =IF(COUNT(AD7:AD14)=0,"NM",AVERAGE(AD7:AD14)) | ... AF18: =IF(COUNT(AF7:AF14)=0,"NM",AVERAGE(AF7:AF14))
B19: Median | Q19: =IF(COUNT(Q7:Q14)=0,"NM",MEDIAN(Q7:Q14)) | R19: =IF(COUNT(R7:R14)=0,"NM",MEDIAN(R7:R14)) | S19: =IF(COUNT(S7:S14)=0,"NM",MEDIAN(S7:S14)) | T19: =IF(COUNT(T7:T14)=0,"NM",MEDIAN(T7:T14)) | W19: =IF(COUNT(W7:W14)=0,"NM",MEDIAN(W7:W14)) | X19: =IF(COUNT(X7:X14)=0,"NM",MEDIAN(X7:X14)) | Y19: =IF(COUNT(Y7:Y14)=0,"NM",MEDIAN(Y7:Y14)) | Z19: =IF(COUNT(Z7:Z14)=0,"NM",MEDIAN(Z7:Z14)) | AA19: =IF(COUNT(AA7:AA14)=0,"NM",MEDIAN(AA7:AA14)) | AB19: =IF(COUNT(AB7:AB14)=0,"NM",MEDIAN(AB7:AB14)) | AC19: =IF(COUNT(AC7:AC14)=0,"NM",MEDIAN(AC7:AC14)) | AD19: =IF(COUNT(AD7:AD14)=0,"NM",MEDIAN(AD7:AD14)) | ... AF19: =IF(COUNT(AF7:AF14)=0,"NM",MEDIAN(AF7:AF14))
B20: 25th Percentile | Q20: =IF(COUNT(Q7:Q14)=0,"NM",PERCENTILE(Q7:Q14,0.25)) | R20: =IF(COUNT(R7:R14)=0,"NM",PERCENTILE(R7:R14,0.25)) | S20: =IF(COUNT(S7:S14)=0,"NM",PERCENTILE(S7:S14,0.25)) | T20: =IF(COUNT(T7:T14)=0,"NM",PERCENTILE(T7:T14,0.25)) | W20: =IF(COUNT(W7:W14)=0,"NM",PERCENTILE(W7:W14,0.25)) | X20: =IF(COUNT(X7:X14)=0,"NM",PERCENTILE(X7:X14,0.25)) | Y20: =IF(COUNT(Y7:Y14)=0,"NM",PERCENTILE(Y7:Y14,0.25)) | Z20: =IF(COUNT(Z7:Z14)=0,"NM",PERCENTILE(Z7:Z14,0.25)) | AA20: =IF(COUNT(AA7:AA14)=0,"NM",PERCENTILE(AA7:AA14,0.25)) | AB20: =IF(COUNT(AB7:AB14)=0,"NM",PERCENTILE(AB7:AB14,0.25)) | AC20: =IF(COUNT(AC7:AC14)=0,"NM",PERCENTILE(AC7:AC14,0.25)) | AD20: =IF(COUNT(AD7:AD14)=0,"NM",PERCENTILE(AD7:AD14,0.25)) | ... AF20: =IF(COUNT(AF7:AF14)=0,"NM",PERCENTILE(AF7:AF14,0.25))
B21: Minimum | Q21: =IF(COUNT(Q7:Q14)=0,"NM",MIN(Q7:Q14)) | R21: =IF(COUNT(R7:R14)=0,"NM",MIN(R7:R14)) | S21: =IF(COUNT(S7:S14)=0,"NM",MIN(S7:S14)) | T21: =IF(COUNT(T7:T14)=0,"NM",MIN(T7:T14)) | W21: =IF(COUNT(W7:W14)=0,"NM",MIN(W7:W14)) | X21: =IF(COUNT(X7:X14)=0,"NM",MIN(X7:X14)) | Y21: =IF(COUNT(Y7:Y14)=0,"NM",MIN(Y7:Y14)) | Z21: =IF(COUNT(Z7:Z14)=0,"NM",MIN(Z7:Z14)) | AA21: =IF(COUNT(AA7:AA14)=0,"NM",MIN(AA7:AA14)) | AB21: =IF(COUNT(AB7:AB14)=0,"NM",MIN(AB7:AB14)) | AC21: =IF(COUNT(AC7:AC14)=0,"NM",MIN(AC7:AC14)) | AD21: =IF(COUNT(AD7:AD14)=0,"NM",MIN(AD7:AD14)) | ... AF21: =IF(COUNT(AF7:AF14)=0,"NM",MIN(AF7:AF14))
B23: =IF($A$6="","Target",$A$6)&" vs. peer median" | Q23: =IF(AND(ISNUMBER(Q6),ISNUMBER(Q19)),Q6-Q19,"NM") | R23: =IF(AND(ISNUMBER(R6),ISNUMBER(R19)),R6-R19,"NM") | S23: =IF(AND(ISNUMBER(S6),ISNUMBER(S19)),S6-S19,"NM") | T23: =IF(AND(ISNUMBER(T6),ISNUMBER(T19)),T6-T19,"NM") | W23: =IF(AND(ISNUMBER(W6),ISNUMBER(W19)),W6/W19-1,"NM") | X23: =IF(AND(ISNUMBER(X6),ISNUMBER(X19)),X6/X19-1,"NM") | Y23: =IF(AND(ISNUMBER(Y6),ISNUMBER(Y19)),Y6/Y19-1,"NM") | Z23: =IF(AND(ISNUMBER(Z6),ISNUMBER(Z19)),Z6/Z19-1,"NM") | AA23: =IF(AND(ISNUMBER(AA6),ISNUMBER(AA19)),AA6/AA19-1,"NM") | AB23: =IF(AND(ISNUMBER(AB6),ISNUMBER(AB19)),AB6/AB19-1,"NM") | AC23: =IF(AND(ISNUMBER(AC6),ISNUMBER(AC19)),AC6/AC19-1,"NM") | AD23: =IF(AND(ISNUMBER(AD6),ISNUMBER(AD19)),AD6/AD19-1,"NM") | ... AF23: =IF(AND(ISNUMBER(AF6),ISNUMBER(AF19)),AF6/AF19-1,"NM")
B24: Margin/growth columns: difference in percentage points. Multiple columns: premium (+) / discount (−) vs. the peer median.

Sheet Valuation
A1: Implied Valuation from Peer Multiples
A2: Implied price = (peer multiple × target metric − net debt for EV multiples) ÷ shares. Multiples and blend flags come from the Dashboard.
A4: Current share price | C4: =Comps!C6
A5: Shares outstanding (mm, implied) | C5: =IFERROR(Comps!D6/Comps!C6,"NM")
A6: Net debt ($mm) | C6: =N(Comps!E6)-N(Comps!F6)
A8: Multiple | B8: Target metric | C8: Type | D8: Metric ($mm) | E8: Target multiple | F8: Peer 25th | G8: Peer median | H8: Peer 75th | I8: Implied @ 25th | J8: Implied @ median | K8: Implied @ 75th | L8: Upside @ median | M8: Use in blend
A9: =IF(Dashboard!$B21="","",Dashboard!$B21) | B9: =IF($A9="","",IFERROR(INDEX(Lists!$B$2:$B$11,MATCH($A9,Lists!$A$2:$A$11,0)),"?")) | C9: =IF($A9="","",IFERROR(INDEX(Lists!$C$2:$C$11,MATCH($A9,Lists!$A$2:$A$11,0)),"?")) | D9: =IF($A9="","",IFERROR(INDEX(Comps!$A$6:$T$6,MATCH($B9,Comps!$A$5:$T$5,0)),"NM")) | E9: =IF($A9="","",IFERROR(INDEX(Comps!$W$6:$AF$6,MATCH($A9,Comps!$W$5:$AF$5,0)),"NM")) | F9: =IF($A9="","",IFERROR(INDEX(Comps!$W$20:$AF$20,MATCH($A9,Comps!$W$5:$AF$5,0)),"NM")) | G9: =IF($A9="","",IFERROR(INDEX(Comps!$W$19:$AF$19,MATCH($A9,Comps!$W$5:$AF$5,0)),"NM")) | H9: =IF($A9="","",IFERROR(INDEX(Comps!$W$17:$AF$17,MATCH($A9,Comps!$W$5:$AF$5,0)),"NM")) | I9: =IF($A9="","",IF(AND(ISNUMBER(F9),ISNUMBER($D9),ISNUMBER($C$5)),IF($D9>0,MAX(0,(F9*$D9-IF($C9="EV",$C$6,0))/$C$5),"NM"),"NM")) | J9: =IF($A9="","",IF(AND(ISNUMBER(G9),ISNUMBER($D9),ISNUMBER($C$5)),IF($D9>0,MAX(0,(G9*$D9-IF($C9="EV",$C$6,0))/$C$5),"NM"),"NM")) | K9: =IF($A9="","",IF(AND(ISNUMBER(H9),ISNUMBER($D9),ISNUMBER($C$5)),IF($D9>0,MAX(0,(H9*$D9-IF($C9="EV",$C$6,0))/$C$5),"NM"),"NM")) | L9: =IF($A9="","",IF(ISNUMBER(J9),J9/$C$4-1,"NM")) | M9: =IF($A9="","",Dashboard!$C21)
A10: =IF(Dashboard!$B22="","",Dashboard!$B22) | B10: =IF($A10="","",IFERROR(INDEX(Lists!$B$2:$B$11,MATCH($A10,Lists!$A$2:$A$11,0)),"?")) | C10: =IF($A10="","",IFERROR(INDEX(Lists!$C$2:$C$11,MATCH($A10,Lists!$A$2:$A$11,0)),"?")) | D10: =IF($A10="","",IFERROR(INDEX(Comps!$A$6:$T$6,MATCH($B10,Comps!$A$5:$T$5,0)),"NM")) | E10: =IF($A10="","",IFERROR(INDEX(Comps!$W$6:$AF$6,MATCH($A10,Comps!$W$5:$AF$5,0)),"NM")) | F10: =IF($A10="","",IFERROR(INDEX(Comps!$W$20:$AF$20,MATCH($A10,Comps!$W$5:$AF$5,0)),"NM")) | G10: =IF($A10="","",IFERROR(INDEX(Comps!$W$19:$AF$19,MATCH($A10,Comps!$W$5:$AF$5,0)),"NM")) | H10: =IF($A10="","",IFERROR(INDEX(Comps!$W$17:$AF$17,MATCH($A10,Comps!$W$5:$AF$5,0)),"NM")) | I10: =IF($A10="","",IF(AND(ISNUMBER(F10),ISNUMBER($D10),ISNUMBER($C$5)),IF($D10>0,MAX(0,(F10*$D10-IF($C10="EV",$C$6,0))/$C$5),"NM"),"NM")) | J10: =IF($A10="","",IF(AND(ISNUMBER(G10),ISNUMBER($D10),ISNUMBER($C$5)),IF($D10>0,MAX(0,(G10*$D10-IF($C10="EV",$C$6,0))/$C$5),"NM"),"NM")) | K10: =IF($A10="","",IF(AND(ISNUMBER(H10),ISNUMBER($D10),ISNUMBER($C$5)),IF($D10>0,MAX(0,(H10*$D10-IF($C10="EV",$C$6,0))/$C$5),"NM"),"NM")) | L10: =IF($A10="","",IF(ISNUMBER(J10),J10/$C$4-1,"NM")) | M10: =IF($A10="","",Dashboard!$C22)
A11: =IF(Dashboard!$B23="","",Dashboard!$B23) | B11: =IF($A11="","",IFERROR(INDEX(Lists!$B$2:$B$11,MATCH($A11,Lists!$A$2:$A$11,0)),"?")) | C11: =IF($A11="","",IFERROR(INDEX(Lists!$C$2:$C$11,MATCH($A11,Lists!$A$2:$A$11,0)),"?")) | D11: =IF($A11="","",IFERROR(INDEX(Comps!$A$6:$T$6,MATCH($B11,Comps!$A$5:$T$5,0)),"NM")) | E11: =IF($A11="","",IFERROR(INDEX(Comps!$W$6:$AF$6,MATCH($A11,Comps!$W$5:$AF$5,0)),"NM")) | F11: =IF($A11="","",IFERROR(INDEX(Comps!$W$20:$AF$20,MATCH($A11,Comps!$W$5:$AF$5,0)),"NM")) | G11: =IF($A11="","",IFERROR(INDEX(Comps!$W$19:$AF$19,MATCH($A11,Comps!$W$5:$AF$5,0)),"NM")) | H11: =IF($A11="","",IFERROR(INDEX(Comps!$W$17:$AF$17,MATCH($A11,Comps!$W$5:$AF$5,0)),"NM")) | I11: =IF($A11="","",IF(AND(ISNUMBER(F11),ISNUMBER($D11),ISNUMBER($C$5)),IF($D11>0,MAX(0,(F11*$D11-IF($C11="EV",$C$6,0))/$C$5),"NM"),"NM")) | J11: =IF($A11="","",IF(AND(ISNUMBER(G11),ISNUMBER($D11),ISNUMBER($C$5)),IF($D11>0,MAX(0,(G11*$D11-IF($C11="EV",$C$6,0))/$C$5),"NM"),"NM")) | K11: =IF($A11="","",IF(AND(ISNUMBER(H11),ISNUMBER($D11),ISNUMBER($C$5)),IF($D11>0,MAX(0,(H11*$D11-IF($C11="EV",$C$6,0))/$C$5),"NM"),"NM")) | L11: =IF($A11="","",IF(ISNUMBER(J11),J11/$C$4-1,"NM")) | M11: =IF($A11="","",Dashboard!$C23)
A12: =IF(Dashboard!$B24="","",Dashboard!$B24) | B12: =IF($A12="","",IFERROR(INDEX(Lists!$B$2:$B$11,MATCH($A12,Lists!$A$2:$A$11,0)),"?")) | C12: =IF($A12="","",IFERROR(INDEX(Lists!$C$2:$C$11,MATCH($A12,Lists!$A$2:$A$11,0)),"?")) | D12: =IF($A12="","",IFERROR(INDEX(Comps!$A$6:$T$6,MATCH($B12,Comps!$A$5:$T$5,0)),"NM")) | E12: =IF($A12="","",IFERROR(INDEX(Comps!$W$6:$AF$6,MATCH($A12,Comps!$W$5:$AF$5,0)),"NM")) | F12: =IF($A12="","",IFERROR(INDEX(Comps!$W$20:$AF$20,MATCH($A12,Comps!$W$5:$AF$5,0)),"NM")) | G12: =IF($A12="","",IFERROR(INDEX(Comps!$W$19:$AF$19,MATCH($A12,Comps!$W$5:$AF$5,0)),"NM")) | H12: =IF($A12="","",IFERROR(INDEX(Comps!$W$17:$AF$17,MATCH($A12,Comps!$W$5:$AF$5,0)),"NM")) | I12: =IF($A12="","",IF(AND(ISNUMBER(F12),ISNUMBER($D12),ISNUMBER($C$5)),IF($D12>0,MAX(0,(F12*$D12-IF($C12="EV",$C$6,0))/$C$5),"NM"),"NM")) | J12: =IF($A12="","",IF(AND(ISNUMBER(G12),ISNUMBER($D12),ISNUMBER($C$5)),IF($D12>0,MAX(0,(G12*$D12-IF($C12="EV",$C$6,0))/$C$5),"NM"),"NM")) | K12: =IF($A12="","",IF(AND(ISNUMBER(H12),ISNUMBER($D12),ISNUMBER($C$5)),IF($D12>0,MAX(0,(H12*$D12-IF($C12="EV",$C$6,0))/$C$5),"NM"),"NM")) | L12: =IF($A12="","",IF(ISNUMBER(J12),J12/$C$4-1,"NM")) | M12: =IF($A12="","",Dashboard!$C24)
A13: =IF(Dashboard!$B25="","",Dashboard!$B25) | B13: =IF($A13="","",IFERROR(INDEX(Lists!$B$2:$B$11,MATCH($A13,Lists!$A$2:$A$11,0)),"?")) | C13: =IF($A13="","",IFERROR(INDEX(Lists!$C$2:$C$11,MATCH($A13,Lists!$A$2:$A$11,0)),"?")) | D13: =IF($A13="","",IFERROR(INDEX(Comps!$A$6:$T$6,MATCH($B13,Comps!$A$5:$T$5,0)),"NM")) | E13: =IF($A13="","",IFERROR(INDEX(Comps!$W$6:$AF$6,MATCH($A13,Comps!$W$5:$AF$5,0)),"NM")) | F13: =IF($A13="","",IFERROR(INDEX(Comps!$W$20:$AF$20,MATCH($A13,Comps!$W$5:$AF$5,0)),"NM")) | G13: =IF($A13="","",IFERROR(INDEX(Comps!$W$19:$AF$19,MATCH($A13,Comps!$W$5:$AF$5,0)),"NM")) | H13: =IF($A13="","",IFERROR(INDEX(Comps!$W$17:$AF$17,MATCH($A13,Comps!$W$5:$AF$5,0)),"NM")) | I13: =IF($A13="","",IF(AND(ISNUMBER(F13),ISNUMBER($D13),ISNUMBER($C$5)),IF($D13>0,MAX(0,(F13*$D13-IF($C13="EV",$C$6,0))/$C$5),"NM"),"NM")) | J13: =IF($A13="","",IF(AND(ISNUMBER(G13),ISNUMBER($D13),ISNUMBER($C$5)),IF($D13>0,MAX(0,(G13*$D13-IF($C13="EV",$C$6,0))/$C$5),"NM"),"NM")) | K13: =IF($A13="","",IF(AND(ISNUMBER(H13),ISNUMBER($D13),ISNUMBER($C$5)),IF($D13>0,MAX(0,(H13*$D13-IF($C13="EV",$C$6,0))/$C$5),"NM"),"NM")) | L13: =IF($A13="","",IF(ISNUMBER(J13),J13/$C$4-1,"NM")) | M13: =IF($A13="","",Dashboard!$C25)
A14: =IF(Dashboard!$B26="","",Dashboard!$B26) | B14: =IF($A14="","",IFERROR(INDEX(Lists!$B$2:$B$11,MATCH($A14,Lists!$A$2:$A$11,0)),"?")) | C14: =IF($A14="","",IFERROR(INDEX(Lists!$C$2:$C$11,MATCH($A14,Lists!$A$2:$A$11,0)),"?")) | D14: =IF($A14="","",IFERROR(INDEX(Comps!$A$6:$T$6,MATCH($B14,Comps!$A$5:$T$5,0)),"NM")) | E14: =IF($A14="","",IFERROR(INDEX(Comps!$W$6:$AF$6,MATCH($A14,Comps!$W$5:$AF$5,0)),"NM")) | F14: =IF($A14="","",IFERROR(INDEX(Comps!$W$20:$AF$20,MATCH($A14,Comps!$W$5:$AF$5,0)),"NM")) | G14: =IF($A14="","",IFERROR(INDEX(Comps!$W$19:$AF$19,MATCH($A14,Comps!$W$5:$AF$5,0)),"NM")) | H14: =IF($A14="","",IFERROR(INDEX(Comps!$W$17:$AF$17,MATCH($A14,Comps!$W$5:$AF$5,0)),"NM")) | I14: =IF($A14="","",IF(AND(ISNUMBER(F14),ISNUMBER($D14),ISNUMBER($C$5)),IF($D14>0,MAX(0,(F14*$D14-IF($C14="EV",$C$6,0))/$C$5),"NM"),"NM")) | J14: =IF($A14="","",IF(AND(ISNUMBER(G14),ISNUMBER($D14),ISNUMBER($C$5)),IF($D14>0,MAX(0,(G14*$D14-IF($C14="EV",$C$6,0))/$C$5),"NM"),"NM")) | K14: =IF($A14="","",IF(AND(ISNUMBER(H14),ISNUMBER($D14),ISNUMBER($C$5)),IF($D14>0,MAX(0,(H14*$D14-IF($C14="EV",$C$6,0))/$C$5),"NM"),"NM")) | L14: =IF($A14="","",IF(ISNUMBER(J14),J14/$C$4-1,"NM")) | M14: =IF($A14="","",Dashboard!$C26)
A16: Blended implied price (avg. of 'Y' rows) | I16: =IFERROR(AVERAGEIFS(I9:I14,$M$9:$M$14,"Y"),"NM") | J16: =IFERROR(AVERAGEIFS(J9:J14,$M$9:$M$14,"Y"),"NM") | K16: =IFERROR(AVERAGEIFS(K9:K14,$M$9:$M$14,"Y"),"NM") | L16: =IF(ISNUMBER(J16),J16/$C$4-1,"NM")

Sheet Peer Screen
A1: Peer Candidate Screen
A2: Every candidate considered, ranked by similarity (0–100). Weights: industry 35, investor grouping 10, size 20, revenue growth 15, EBITDA margin 10, gross margin 10.
A4: Rank | B4: Ticker | C4: Company | D4: Industry | E4: Market cap ($mm) | F4: Rev growth | G4: EBITDA margin | H4: Industry pts | I4: Investor pts | J4: Size pts | K4: Growth pts | L4: EBITDA mgn pts | M4: Gross mgn pts | N4: Total score
A5: 1 | B5: BABA | C5: Alibaba Group Holding Limited | D5: Internet Retail | E5: 320000 | F5: 0.06 | G5: 0.18115942 | H5: 35 | I5: 0 | J5: 11.2 | K5: 12.5 | L5: 8.8 | M5: 7.7 | N5: 75.2
A6: 2 | B6: PDD | C6: PDD Holdings Inc. | D6: Internet Retail | E6: 170000 | F6: 0.1 | G6: 0.28571429 | H6: 35 | I6: 0 | J6: 8.5 | K6: 14.5 | L6: 7.7 | M6: 7.6 | N6: 73.3
A7: 3 | B7: MELI | C7: MercadoLibre, Inc. | D7: Internet Retail | E7: 120000 | F7: 0.37 | G7: 0.15 | H7: 35 | I7: 0 | J7: 7 | K7: 2 | L7: 7.8 | M7: 9.1 | N7: 60.9
A8: 4 | B8: EBAY | C8: eBay Inc. | D8: Internet Retail | E8: 41000 | F8: 0.04 | G8: 0.31428571 | H8: 35 | I8: 0 | J8: 2.3 | K8: 11.5 | L8: 6.7 | M8: 4.7 | N8: 60.3
A9: 5 | B9: CPNG | C9: Coupang, Inc. | D9: Internet Retail | E9: 54000 | F9: 0.18 | G9: 0.048484848 | H9: 35 | I9: 0 | J9: 3.5 | K9: 11.5 | L9: 4.4 | M9: 5.3 | N9: 59.7
A10: 6 | B10: JD | C10: JD.com, Inc. | D10: Internet Retail | E10: 50000 | F10: 0.11 | G10: 0.040625 | H10: 35 | I10: 0 | J10: 3.2 | K10: 15 | L10: 4.1 | M10: 1.6 | N10: 58.9
A11: 7 | B11: CHWY | C11: Chewy, Inc. | D11: Internet Retail | E11: 16000 | F11: 0.08 | G11: 0.05 | H11: 35 | I11: 0 | J11: 0 | K11: 13.5 | L11: 4.5 | M11: 5 | N11: 57.9
A12: 8 | B12: GOOGL | C12: Alphabet Inc. | D12: Internet Content & Information | E12: 2900000 | F12: 0.14 | G12: 0.38961039 | H12: 0 | I12: 10 | J12: 19.2 | K12: 13.5 | L12: 4.2 | M12: 7.4 | N12: 54.3
A13: 9 | B13: WMT | C13: Walmart Inc. | D13: Discount Stores | E13: 800000 | F13: 0.05 | G13: 0.060869565 | H13: 0 | I13: 10 | J13: 15.2 | K13: 12 | L13: 4.8 | M13: 3.8 | N13: 45.9
A14: 10 | B14: MSFT | C14: Microsoft Corporation | D14: Software - Infrastructure | E14: 3800000 | F14: 0.16 | G14: 0.55172414 | H14: 0 | I14: 10 | J14: 18 | K14: 12.5 | L14: 0 | M14: 5.1 | N14: 45.6
A15: 11 | B15: META | C15: Meta Platforms, Inc. | D15: Internet Content & Information | E15: 1800000 | F15: 0.2 | G15: 0.54054054 | H15: 0 | I15: 10 | J15: 18.8 | K15: 10.5 | L15: 0 | M15: 2 | N15: 41.3

Sheet Lists
A1: Multiple | B1: Target metric (Comps header) | C1: Type | D1: Why use it | E1: NM cap
A2: EV / LTM Revenue | B2: LTM Revenue ($mm) | C2: EV | D2: Capital-structure neutral; works even when earnings are depressed. | E2: =Comps!W$4
A3: EV / NTM Revenue | B3: NTM Revenue ($mm) | C3: EV | D3: Forward revenue captures growth the market is already pricing in. | E3: =Comps!X$4
A4: EV / Gross Profit | B4: LTM Gross Profit ($mm) | C4: EV | D4: Normalises for different revenue mixes (e.g. marketplace vs. 1P sales). | E4: =Comps!Y$4
A5: EV / EBITDA | B5: LTM EBITDA ($mm) | C5: EV | D5: Most common cross-company multiple: ignores leverage, tax and D&A differences. | E5: =Comps!Z$4
A6: EV / EBIT | B6: LTM EBIT ($mm) | C6: EV | D6: Like EV/EBITDA but charges for capex intensity via D&A. | E6: =Comps!AA$4
A7: P / E (LTM) | B7: LTM Net Income ($mm) | C7: Equity | D7: What investors pay per dollar of trailing earnings to equity holders. | E7: =Comps!AB$4
A8: P / E (Forward) | B8: Forward Earnings ($mm) | C8: Equity | D8: Market's primary equity multiple; based on consensus next-year EPS. | E8: =Comps!AC$4
A9: P / FCF | B9: LTM FCF ($mm) | C9: Equity | D9: Cash actually generated for shareholders after capex. | E9: =Comps!AD$4
A10: P / Operating Cash Flow | B10: LTM Op. Cash Flow ($mm) | C10: Equity | D10: Cash earnings before capex; a proxy for FFO in real estate. | E10: =Comps!AE$4
A11: P / Book | B11: Book Value ($mm) | C11: Equity | D11: Key for balance-sheet businesses where assets are marked near fair value. | E11: =Comps!AF$4
A13: Lookup table used by the Dashboard dropdowns and the Valuation sheet. Edit the 'Why use it' text freely; keep the first three columns as they are.

Sheet Notes
A1: How to use
A2: 1 | B2: Type a company name ('Amazon') or ticker ('AMZN') into the yellow cell on the Dashboard.
A3: 2 | B3: Click the xlwings ribbon tab → Run main. Python pulls Yahoo Finance data, picks peers and multiples, and writes them into the blue cells. Everything else is formulas.
A4: 3 | B4: Change the multiples with the dropdowns and the Y/N blend flags on the Dashboard – no refresh needed. Overwrite any blue input on the Comps sheet to test your own numbers.
A5: Keep the name | B5: Run main calls the Python file with the same name as the workbook (CompsModel.py). To keep a snapshot of a company, use File → Save a Copy.
A7: Methodology
A8: Peers | B8: Candidates come from Yahoo's industry constituents, Yahoo's 'people also watch' list and (if thin) sector leaders, scored on industry, investor grouping, size, growth and margins.
A9: Multiples | B9: Picked by profile (financial, REIT, unprofitable, high-growth, capital-intensive, mature). EV = market cap + total debt − cash.
A10: NM | B10: Not meaningful: negative/zero denominator or above the cap in row 4 of Comps. Excluded from stats.
A11: NTM Revenue | B11: Time-weighted blend of consensus current-FY and next-FY revenue.
A12: Fwd Earnings | B12: Market cap ÷ Yahoo forward P/E (consensus next fiscal year EPS).
A13: EBIT | B13: LTM revenue × LTM operating margin.
A14: Currency | B14: ADR financials are converted to the trading currency at spot FX.
A15: Limitations | B15: Yahoo data can lag filings and is not adjusted for one-offs, leases, minority interest or preferreds. Sanity-check key inputs against the 10-K/10-Q before presenting.
